{
  "user_id": "6bf28ec8-acb3-477a-9cad-9d2e1274e078",
  "platform_data": {
    "name": "Citra Kusuma",
    "email": "citra.kusuma72@example.com",
    "active_courses": [
      "Belajar Membuat Mixed Reality"
    ],
    "active_tutorials": 20,
    "completed_tutorials": 20,
    "is_graduated": 0,
    "exam_score": "",
    "submission_rating": "",
    "course_progress": {
      "Belajar Membuat Mixed Reality": 0
    }
  },
  "learning_profile": {
    "goals": [],
    "skills": {},
    "weaknesses": [],
    "strengths": [],
    "current_focus": {
      "course": "Belajar Membuat Mixed Reality",
      "module": 0
    },
    "learning_style": null,
    "progress_score": {},
    "history": []
  },
  "created_at": "2025-12-11T13:48:16.411Z",
  "updated_at": 1765460896411,
  "progress_history": [],
  "roadmap_progress": {
    "job_role": null,
    "created_at": 1765460896411,
    "last_updated": 1765460896411,
    "skills_status": {},
    "subskills": []
  }
}