{
  "user_id": "df756597-7b08-49c7-bcc9-c17f1da126b4",
  "platform_data": {
    "name": "Fira Ramadhan",
    "email": "fira.ramadhan82@example.com",
    "active_courses": [
      "Belajar Prinsip Pemrograman SOLID"
    ],
    "active_tutorials": 41,
    "completed_tutorials": 36,
    "is_graduated": 1,
    "exam_score": "92",
    "submission_rating": "",
    "course_progress": {
      "Belajar Prinsip Pemrograman SOLID": 0
    }
  },
  "learning_profile": {
    "goals": [],
    "skills": {},
    "weaknesses": [],
    "strengths": [],
    "current_focus": {
      "course": "Belajar Prinsip Pemrograman SOLID",
      "module": 0
    },
    "learning_style": null,
    "progress_score": {},
    "history": []
  },
  "created_at": "2025-12-11T13:48:16.421Z",
  "updated_at": 1765460896421,
  "progress_history": [],
  "roadmap_progress": {
    "job_role": null,
    "created_at": 1765460896421,
    "last_updated": 1765460896421,
    "skills_status": {},
    "subskills": []
  }
}